tap_kafka/__init__.py
tap_kafka/common.py
tap_kafka/errors.py
tap_kafka/sync.py
tap_kafka/serialization/__init__.py
tap_kafka/serialization/json_with_no_schema.py
tap_kafka/serialization/protobuf.py
pipelinewise_tap_kafka-8.2.1.dist-info/LICENSE
pipelinewise_tap_kafka-8.2.1.dist-info/METADATA
pipelinewise_tap_kafka-8.2.1.dist-info/WHEEL
pipelinewise_tap_kafka-8.2.1.dist-info/entry_points.txt
pipelinewise_tap_kafka-8.2.1.dist-info/top_level.txt
pipelinewise_tap_kafka-8.2.1.dist-info/RECORD
