Metadata-Version: 2.1
Name: pipelinewise-tap-kafka
Version: 8.2.1
Summary: Singer.io tap for extracting data from Kafka topic - PipelineWise compatible
Home-page: https://github.com/transferwise/pipelinewise-tap-kafka
Author: TransferWise
Classifier: License :: OSI Approved :: GNU Affero General Public License v3
Classifier: Programming Language :: Python :: 3 :: Only
License-File: LICENSE
Requires-Dist: pipelinewise-singer-python ==2.*
Requires-Dist: dpath ==2.1.*
Requires-Dist: confluent-kafka[protobuf] ==2.3.*
Requires-Dist: grpcio-tools ==1.57.*
Provides-Extra: test
Requires-Dist: pytest ==7.4.* ; extra == 'test'
Requires-Dist: pylint ==2.17.* ; extra == 'test'
Requires-Dist: pytest-cov ==4.0.* ; extra == 'test'
